frappe_client/__init__.py
frappe_client/frappe_client.py
frappe_client/frappe_exceptions.py
py_frappe_client-1.3.0.dist-info/METADATA
py_frappe_client-1.3.0.dist-info/WHEEL
py_frappe_client-1.3.0.dist-info/top_level.txt
py_frappe_client-1.3.0.dist-info/RECORD
